{
  "date": "2025-04-28",
  "cards": [
    {
      "code": "w1",
      "name": "Ace of Wands, reversed",
      "upright": false,
      "interpretation": "delays, blocks, lack of passion, lack of energy, hesitancy, creative blocks"
    },
    {
      "code": "p14",
      "name": "King of Pentacles, reversed",
      "upright": false,
      "interpretation": "greed, materialistic, wasteful, chauvanist, poor financial decisions, gambler, exploitative, possessive"
    },
    {
      "code": "p4",
      "name": "4 of Pentacles",
      "upright": true,
      "interpretation": "possessiveness, insecurity, hoarding, stinginess, stability, security, savings, materialism, wealth, frugality, boundaries, guardedness"
    }
  ]
}
